pygelf/__init__.py
pygelf/gelf.py
pygelf/handlers.py
pygelf-0.4.3.dist-info/licenses/LICENSE
pygelf-0.4.3.dist-info/METADATA
pygelf-0.4.3.dist-info/WHEEL
pygelf-0.4.3.dist-info/top_level.txt
pygelf-0.4.3.dist-info/RECORD
